swizzle/__init__.py
swizzle/trie.py
swizzle/utils.py
swizzle-2.6.1.dist-info/licenses/LICENSE
swizzle-2.6.1.dist-info/METADATA
swizzle-2.6.1.dist-info/WHEEL
swizzle-2.6.1.dist-info/top_level.txt
swizzle-2.6.1.dist-info/RECORD
