Metadata-Version: 2.4
Name: swizzle
Version: 2.6.1
Summary: Swizzle enables the retrieval of multiple attributes, similar to swizzling in computer graphics.
Author-email: "Jan T. Müller" <mail@jantmueller.com>
License: MIT
Project-URL: homepage, https://github.com/janthmueller/swizzle
Project-URL: documentation, https://janthmueller.github.io/swizzle/
Project-URL: source, https://github.com/janthmueller/swizzle
Project-URL: tracker, https://github.com/janthmueller/swizzle/issues
Keywords: swizzle,attributes,graphics,development
Classifier: Intended Audience :: Developers
Classifier: Topic :: Software Development :: Libraries :: Python Modules
Classifier: License :: OSI Approved :: MIT License
Classifier: Operating System :: OS Independent
Classifier: Programming Language :: Python :: 3 :: Only
Requires-Python: >=3.8
License-File: LICENSE
Dynamic: license-file
